nti/__init__.py
nti/testing/__init__.py
nti/testing/base.py
nti/testing/matchers.py
nti/testing/mock.py
nti/testing/time.py
nti/testing/zodb.py
nti/testing/layers/__init__.py
nti/testing/layers/cleanup.py
nti/testing/layers/postgres.py
nti/testing/layers/zope.py
nti/testing/layers/tests/__init__.py
nti/testing/layers/tests/test_postgres.py
nti/testing/tests/__init__.py
nti/testing/tests/test_base.py
nti/testing/tests/test_component_cleanup_broken.txt
nti/testing/tests/test_layers.py
nti/testing/tests/test_main.py
nti/testing/tests/test_matchers.py
nti/testing/tests/test_time.py
nti/testing/tests/test_zodb.py
nti_testing-4.4.0.dist-info/licenses/LICENSE
nti_testing-4.4.0.dist-info/METADATA
nti_testing-4.4.0.dist-info/WHEEL
nti_testing-4.4.0.dist-info/top_level.txt
nti_testing-4.4.0.dist-info/zip-safe
nti_testing-4.4.0.dist-info/RECORD
