Metadata-Version: 2.4
Name: nti.testing
Version: 4.4.0
Summary: Support for testing code
Home-page: https://github.com/OpenNTI/nti.testing
Author: Jason Madden
Author-email: jason@nextthought.com
License: Apache
Project-URL: Documentation, https://ntitesting.readthedocs.io/en/latest/
Keywords: nose2 testing zope3 ZTK hamcrest
Classifier: Intended Audience :: Developers
Classifier: Natural Language :: English
Classifier: Operating System :: OS Independent
Classifier: License :: OSI Approved :: Apache Software License
Classifier: Programming Language :: Python :: 3
Classifier: Programming Language :: Python :: 3 :: Only
Classifier: Programming Language :: Python :: 3.10
Classifier: Programming Language :: Python :: 3.11
Classifier: Programming Language :: Python :: 3.12
Classifier: Programming Language :: Python :: 3.13
Classifier: Programming Language :: Python :: 3.14
Classifier: Programming Language :: Python :: Implementation :: CPython
Classifier: Programming Language :: Python :: Implementation :: PyPy
Classifier: Topic :: Software Development :: Testing
Classifier: Framework :: Zope3
Requires-Python: >=3.10
License-File: LICENSE
Requires-Dist: zope.interface>=5.4.0
Requires-Dist: pyhamcrest
Requires-Dist: six
Requires-Dist: transaction
Requires-Dist: zope.component
Requires-Dist: zope.configuration
Requires-Dist: zope.dottedname
Requires-Dist: zope.exceptions
Requires-Dist: zope.schema
Requires-Dist: zope.testing
Provides-Extra: zodb
Requires-Dist: ZODB>=5.6.0; extra == "zodb"
Provides-Extra: test
Requires-Dist: Acquisition; extra == "test"
Requires-Dist: zope.testrunner; extra == "test"
Requires-Dist: testgres>=1.11; extra == "test"
Requires-Dist: psycopg2-binary; platform_python_implementation != "PyPy" and extra == "test"
Provides-Extra: test-zodb
Requires-Dist: zope.site; extra == "test-zodb"
Provides-Extra: docs
Requires-Dist: Sphinx; extra == "docs"
Requires-Dist: furo; extra == "docs"
Requires-Dist: Acquisition; extra == "docs"
Requires-Dist: zope.testrunner; extra == "docs"
Requires-Dist: testgres>=1.11; extra == "docs"
Requires-Dist: psycopg2-binary; platform_python_implementation != "PyPy" and extra == "docs"
Provides-Extra: testgres
Requires-Dist: testgres>=1.11; extra == "testgres"
Requires-Dist: psycopg2-binary; platform_python_implementation != "PyPy" and extra == "testgres"
Dynamic: author
Dynamic: author-email
Dynamic: classifier
Dynamic: description
Dynamic: home-page
Dynamic: keywords
Dynamic: license
Dynamic: license-file
Dynamic: project-url
Dynamic: provides-extra
Dynamic: requires-dist
Dynamic: requires-python
Dynamic: summary
